{
  "fonts": {
    "lxgw": {
      "path": "json/LXGW WenKai_Regular.json",
      "size": 199825
    }
  },
  "textures": {
    "img/earth.jpg": 19566,
    "img/BeachBallColor.jpg": 5807,
    "img/stone.png": 637625,
    "img/woodTexture.jpg": 749450,
    "img/project-placeholder.png": 155270,
    "img/lensflare0.png": 32296,
    "img/spark.png": 1788
  },
  "ammo": {
    "ammo/ammo.js": 1881243,
    "ammo/ammo.wasm.js": 393767,
    "ammo/ammo.wasm.wasm": 651386,
    "total": 2926396
  },
  "totals": {
    "fonts": 199825,
    "textures": 1601802,
    "ammo": 2926396,
    "all": 4728023
  }
}